deepchain/__init__.py
deepchain/version.py
deepchain/cli/__init__.py
deepchain/cli/apps.py
deepchain/cli/apps_utils.py
deepchain/cli/auth.py
deepchain/cli/cli_utils.py
deepchain/cli/config.ini
deepchain/cli/config.py
deepchain/cli/deepchain_cli.py
deepchain/cli/deploy.py
deepchain/cli/download.py
deepchain/cli/inference.py
deepchain/cli/scaffold.py
deepchain/cli/set_backend.py
deepchain/components/__init__.py
deepchain/components/loading_utils.py
deepchain/components/scorers/__init__.py
deepchain/components/scorers/base_scorer.py
deepchain/models/__init__.py
deepchain/models/tf_models.py
deepchain/models/torch_mlp.py
deepchain/models/torch_model.py
deepchain/models/utils.py
deepchain/utils/__init__.py
deepchain/utils/constants.py
deepchain/utils/exceptions.py
deepchain/utils/get_input.py
deepchain/utils/logger.py
deepchain/utils/validation.py
deepchain_apps-0.1.12.dist-info/LICENSE
deepchain_apps-0.1.12.dist-info/METADATA
deepchain_apps-0.1.12.dist-info/WHEEL
deepchain_apps-0.1.12.dist-info/entry_points.txt
deepchain_apps-0.1.12.dist-info/top_level.txt
deepchain_apps-0.1.12.dist-info/RECORD
