Metadata-Version: 2.1
Name: deepchain-apps
Version: 0.1.12
Summary: Define a personnal app to deploy on DeepChain.bio
Home-page: UNKNOWN
Author: Instadeep
Author-email: a.delfosse@instadeep.com
License: Apache-2.0
Platform: UNKNOWN
Classifier: License :: OSI Approved :: Apache Software License
Classifier: Operating System :: OS Independent
Classifier: Programming Language :: Python :: 3.7
Classifier: Topic :: Scientific/Engineering :: Artificial Intelligence
Classifier: Topic :: Scientific/Engineering :: Bio-Informatics
Classifier: Topic :: Software Development
Requires-Python: >=3.7
License-File: LICENSE
Requires-Dist: bio-transformers (>=0.1.17)
Requires-Dist: bio-datasets (>=0.0.4)
Requires-Dist: matplotlib (==3.4.1)
Requires-Dist: numpy (<1.19,>=1.16)
Requires-Dist: pandas (>=1.2.3)
Requires-Dist: pytorch-lightning (>=1.3.3)
Requires-Dist: requests (>=2.23.0)
Requires-Dist: scikit-learn (>=0.22.2)
Requires-Dist: tensorflow (<2.4,>=2.3.0)
Requires-Dist: torch (<1.9.0,>=1.7.0)
Requires-Dist: tqdm (>=4.60.0)
